{
  "en": {
    "pageTitle": "Shop",
    "pageDescription": "Discover our complete collection of motorcycle gear and browse by categories",
    "breadcrumbs": {
      "home": "Home",
      "shop": "Shop"
    },
    "filters": {
      "title": "Filters",
      "clearAll": "Clear All",
      "apply": "Apply Filters",
      "categories": "Categories",
      "languages": "Languages", 
      "quality": "Quality",
      "availability": "Availability",
      "price": "Price"
    },
    "collections": {
      "count": "collections",
      "sortBy": "Sort by:",
      "bestSelling": "Best Selling",
      "priceLow": "Price: Low to High",
      "priceHigh": "Price: High to Low",
      "newest": "Newest",
      "oldest": "Oldest"
    },
    "collections": {
      "title": "Browse by Category",
      "description": "Explore our curated motorcycle gear collections",
      "exploreCollection": "Explore Collection"
    },
    "whyChooseUs": {
      "title": "Why Choose Our Motorcycle Gear?",
      "description": "Experience the best in motorcycle safety and style",
      "instantAccess": {
        "title": "Premium Materials",
        "description": "High-quality leather, textile, and protective gear for all riders"
      },
      "premiumQuality": {
        "title": "Safety First", 
        "description": "CE certified protection with advanced impact technology"
      },
      "support": {
        "title": "Expert Support",
        "description": "Professional advice and support from motorcycle enthusiasts"
      }
    },
    "stats": {
      "title": "Why Choose Us?",
      "description": "Trusted by thousands of riders worldwide",
      "customerRating": "Customer Rating",
      "happyCustomers": "Happy Riders", 
      "support": "Expert Support",
      "quality": "Safety Rating"
    },
    "newsletter": {
      "title": "Stay Updated",
      "description": "Get the latest gear releases, safety tips, and exclusive rider offers",
      "emailPlaceholder": "Enter your email",
      "subscribeButton": "Subscribe"
    },
    "badges": {
      "sale": "Sale"
    }
  },
  "fr": {
    "pageTitle": "Boutique",
    "pageDescription": "Découvrez notre collection complète d'équipements moto et parcourez par catégories",
    "breadcrumbs": {
      "home": "Accueil",
      "shop": "Boutique"
    },
    "filters": {
      "title": "Filtres",
      "clearAll": "Tout effacer",
      "apply": "Appliquer les filtres",
      "categories": "Catégories",
      "languages": "Langues",
      "quality": "Qualité", 
      "availability": "Disponibilité",
      "price": "Prix"
    },
    "collections": {
      "count": "produits",
      "sortBy": "Trier par:",
      "bestSelling": "Meilleures ventes",
      "priceLow": "Prix: Bas à élevé",
      "priceHigh": "Prix: Élevé à bas",
      "newest": "Plus récent",
      "oldest": "Plus ancien"
    },
    "collections": {
      "title": "Parcourir par catégorie",
      "description": "Explorez nos collections d'équipements moto organisées",
      "exploreCollection": "Explorer la collection"
    },
    "whyChooseUs": {
      "title": "Pourquoi choisir notre équipement moto?",
      "description": "Découvrez le meilleur en sécurité et style moto",
      "instantAccess": {
        "title": "Matériaux premium",
        "description": "Cuir, textile et équipements de protection de haute qualité pour tous les pilotes"
      },
      "premiumQuality": {
        "title": "Sécurité d'abord",
        "description": "Protection certifiée CE avec technologie d'impact avancée"
      },
      "support": {
        "title": "Support expert",
        "description": "Conseils et support professionnels d'enthousiastes de la moto"
      }
    },
    "stats": {
      "title": "Pourquoi nous choisir?",
      "description": "Fait confiance par des milliers de pilotes dans le monde",
      "customerRating": "Note client",
      "happyCustomers": "Pilotes satisfaits",
      "support": "Support expert", 
      "quality": "Note de sécurité"
    },
    "newsletter": {
      "title": "Restez informé",
      "description": "Recevez les dernières sorties d'équipements, conseils de sécurité et offres exclusives pour pilotes",
      "emailPlaceholder": "Entrez votre email",
      "subscribeButton": "S'abonner"
    },
    "badges": {
      "sale": "Promotion"
    }
  },
  "de": {
    "pageTitle": "Shop",
    "pageDescription": "Entdecken Sie unsere komplette Sammlung von Motorradausrüstung und durchsuchen Sie nach Kategorien",
    "breadcrumbs": {
      "home": "Startseite",
      "shop": "Shop"
    },
    "filters": {
      "title": "Filter",
      "clearAll": "Alle löschen",
      "apply": "Filter anwenden",
      "categories": "Kategorien",
      "languages": "Sprachen",
      "quality": "Qualität",
      "availability": "Verfügbarkeit", 
      "price": "Preis"
    },
    "collections": {
      "count": "Produkte",
      "sortBy": "Sortieren nach:",
      "bestSelling": "Bestseller",
      "priceLow": "Preis: Niedrig zu hoch",
      "priceHigh": "Preis: Hoch zu niedrig",
      "newest": "Neueste",
      "oldest": "Älteste"
    },
    "collections": {
      "title": "Nach Kategorie durchsuchen",
      "description": "Entdecken Sie unsere kuratierten Motorradausrüstungs-Sammlungen",
      "exploreCollection": "Sammlung erkunden"
    },
    "whyChooseUs": {
      "title": "Warum unsere Motorradausrüstung wählen?",
      "description": "Erleben Sie das Beste in Motorradsicherheit und Stil",
      "instantAccess": {
        "title": "Premium-Materialien",
        "description": "Hochwertiges Leder, Textilien und Schutzausrüstung für alle Fahrer"
      },
      "premiumQuality": {
        "title": "Sicherheit zuerst",
        "description": "CE-zertifizierter Schutz mit fortschrittlicher Aufpralltechnologie"
      },
      "support": {
        "title": "Experten-Support",
        "description": "Professionelle Beratung und Support von Motorrad-Enthusiasten"
      }
    },
    "stats": {
      "title": "Warum uns wählen?",
      "description": "Vertraut von Tausenden von Fahrern weltweit",
      "customerRating": "Kundenbewertung",
      "happyCustomers": "Zufriedene Fahrer",
      "support": "Experten-Support",
      "quality": "Sicherheitsbewertung"
    },
    "newsletter": {
      "title": "Bleiben Sie informiert",
      "description": "Erhalten Sie die neuesten Ausrüstungsveröffentlichungen, Sicherheitstipps und exklusive Fahrerangebote",
      "emailPlaceholder": "E-Mail eingeben",
      "subscribeButton": "Abonnieren"
    },
    "badges": {
      "sale": "Angebot"
    }
  }
}
