{
  "title": "Meilleures Ventes - Top Équipement Course",
  "description": "Découvrez nos articles de pilote les plus populaires. Des hoodies de course les plus vendus aux t-shirts de culture automobile les mieux notés, trouvez l'équipement automobile que les pilotes préfèrent.",
  "hero": {
    "title": "Meilleures Ventes",
    "subtitle": "Découvrez nos articles de pilote les plus populaires",
    "cta1": "Acheter les Collections",
    "cta2": "Nouveautés"
  },
  "sections": {
    "features": {
      "title": "Produits les Mieux Notés",
      "subtitle": "Nos articles les plus populaires aimés par les pilotes du monde entier"
    },
    "collections": {
      "title": "Collections les Plus Vendues",
      "subtitle": "Explorez nos catégories de produits les plus performantes"
    }
  },
  "features": [
    {
      "title": "Hoodies de Course",
      "description": "Nos hoodies de course les plus populaires avec des designs authentiques et des matériaux de qualité premium."
    },
    {
      "title": "T-shirts Culture Auto",
      "description": "T-shirts les plus vendus célébrant la culture automobile et l'héritage de la course."
    },
    {
      "title": "Équipement Professionnel",
      "description": "Équipement de course professionnel et accessoires les mieux notés."
    }
  ],
  "collections": [
    {
      "title": "Collection Street Racing",
      "description": "Nos hoodies et vêtements de street racing les plus vendus",
      "link": "/street-racing-hoodies",
      "linkText": "Acheter Best Sellers"
    },
    {
      "title": "Série Professionnelle F1",
      "description": "Combinaisons de course F1 et équipement professionnel les mieux notés",
      "link": "/f1-professional",
      "linkText": "Acheter Best Sellers"
    },
    {
      "title": "Champions Rally",
      "description": "Hoodies et accessoires de course rally les plus populaires",
      "link": "/rally-hoodies",
      "linkText": "Acheter Best Sellers"
    }
  ],
  "cta": {
    "title": "Achetez nos Meilleures Ventes",
    "subtitle": "Rejoignez des milliers de pilotes qui font confiance à nos articles les mieux notés",
    "button1": "Voir Toutes les Collections",
    "button2": "Voir les Nouveautés"
  }
}


